aft_code/__init__.py
aft_code/core.py
arithmagic/__init__.py
arithmagic/core.py
aft_code-1.0.0.dist-info/METADATA
aft_code-1.0.0.dist-info/WHEEL
aft_code-1.0.0.dist-info/top_level.txt
aft_code-1.0.0.dist-info/RECORD
