Metadata-Version: 2.4
Name: aft-code
Version: 1.0.0
Summary: working with file packages
Requires: ujson
Requires-Python: >=3.11
Dynamic: description
Dynamic: description-content-type
Dynamic: requires
Dynamic: requires-python
Dynamic: summary
